softy/__init__.py
softy-0.0.4.dist-info/METADATA
softy-0.0.4.dist-info/WHEEL
softy-0.0.4.dist-info/licenses/LICENSE
softy-0.0.4.dist-info/RECORD
