Metadata-Version: 2.1
Name: softy
Version: 0.0.4
Summary: Python Softy
Project-URL: Homepage, https://github.com/jackmuskopf/softy
Project-URL: Bug Tracker, https://github.com/jackmuskopf/softy/issues
Author-email: Jack Muskopf <jam.muskopf@gmail.com>
License-File: LICENSE
Classifier: License :: OSI Approved :: MIT License
Classifier: Operating System :: OS Independent
Classifier: Programming Language :: Python :: 3
Requires-Python: >=3.7
